README.md
setup.py
knotify/__init__.py
knotify/base_pusher.py
knotify/exception.py
knotify/handler.py
knotify/pusher.py
knotify/pusher_cluster.py
knotify/utils.py
knotify.egg-info/PKG-INFO
knotify.egg-info/SOURCES.txt
knotify.egg-info/dependency_links.txt
knotify.egg-info/top_level.txt