Metadata-Version: 2.1
Name: knotify
Version: 0.0.1
Summary: A simple notification pusher
Home-page: https://github.com/GeorgeMiao219/Knotify
Author: George Miao
Author-email: ge@georgemiao.com
License: UNKNOWN
Platform: UNKNOWN
Classifier: Programming Language :: Python :: 3
Classifier: License :: OSI Approved :: MIT License
Classifier: Operating System :: OS Independent
Requires-Python: >=3.6
